{"frameRate":24,"name":"logoanime","version":"5.5","compatibleVersion":"5.5","armature":[{"type":"MovieClip","frameRate":24,"name":"logoanime","bone":[{"name":"root"},{"name":"main","parent":"root"},{"name":"red","parent":"root"},{"name":"bg","parent":"root"},{"name":"blue","parent":"root"},{"name":"logo","parent":"root"},{"name":"blood","parent":"root"},{"name":"world","parent":"root"}],"slot":[{"displayIndex":-1,"name":"world","parent":"world"},{"displayIndex":-1,"name":"bg","parent":"bg"},{"displayIndex":-1,"name":"blue","parent":"blue"},{"displayIndex":-1,"name":"red","parent":"red"},{"displayIndex":-1,"name":"main","parent":"main"},{"displayIndex":-1,"name":"logo","parent":"logo"},{"displayIndex":-1,"name":"blood","parent":"blood"}],"skin":[{"slot":[{"name":"main","display":[{"name":"main"}]},{"name":"red","display":[{"name":"red"}]},{"name":"logo","display":[{"name":"logo"}]},{"name":"bg","display":[{"name":"bg"}]},{"name":"blood","display":[{"name":"blood"}]},{"name":"blue","display":[{"name":"blue"}]},{"name":"world","display":[{"name":"world"}]}]}],"animation":[{"duration":40,"playTimes":0,"name":"newAnimation","bone":[{"name":"main","translateFrame":[{"duration":4},{"duration":6,"tweenEasing":0,"x":-2.88,"y":155.24},{"duration":15,"tweenEasing":0,"x":-2.88,"y":0.28},{"duration":15,"x":-2.88,"y":-4.32}],"rotateFrame":[{"duration":10},{"duration":15,"tweenEasing":0},{"duration":15,"rotate":-0.22}]},{"name":"red","translateFrame":[{"duration":18},{"duration":9,"tweenEasing":0,"x":-2.1,"y":2.32},{"duration":7,"tweenEasing":0,"x":-6.39,"y":1.98},{"duration":6,"x":-5.34,"y":-4.32}]},{"name":"bg","translateFrame":[{"duration":14},{"tweenEasing":0},{"duration":4,"tweenEasing":0,"x":1.05},{"duration":21}],"scaleFrame":[{"duration":14},{"tweenEasing":0,"x":0.6,"y":0.6},{"duration":4,"tweenEasing":0,"x":1.2,"y":1.2},{"duration":21}]},{"name":"blue","translateFrame":[{"duration":18},{"duration":9,"tweenEasing":0,"x":-6.3,"y":0.91},{"duration":7,"tweenEasing":0,"x":-0.16,"y":2.33},{"duration":6,"x":0.89,"y":-3.97}]},{"name":"blood","translateFrame":[{"duration":3,"tweenEasing":0,"x":-663.58,"y":1.36},{"duration":3,"tweenEasing":0,"x":-126.14},{"duration":34,"x":-146.23,"y":-7.35}],"scaleFrame":[{"duration":3,"tweenEasing":0,"x":0.8},{"duration":3,"tweenEasing":0,"x":0.8},{"duration":34}]},{"name":"world","translateFrame":[{"duration":3,"tweenEasing":0,"x":658.93,"y":-5.25},{"duration":3,"tweenEasing":0,"x":145.54,"y":20.71},{"duration":34,"x":145.54,"y":16.51}],"scaleFrame":[{"duration":3,"tweenEasing":0},{"duration":3,"tweenEasing":0,"x":0.8},{"duration":34}]}],"slot":[{"name":"main","displayFrame":[{"duration":4,"value":-1},{"duration":36}],"colorFrame":[{"duration":4},{"duration":6,"tweenEasing":0,"value":{"aM":0}},{"duration":15,"tweenEasing":0},{"duration":11},{"duration":4,"value":{"aM":0}}]},{"name":"red","displayFrame":[{"duration":18,"value":-1},{"duration":22}],"colorFrame":[{"duration":27},{"duration":7,"tweenEasing":0},{"duration":6,"value":{"aM":0}}]},{"name":"bg","displayFrame":[{"duration":14,"value":-1},{"duration":26}],"colorFrame":[{"duration":14},{"tweenEasing":0,"value":{"aM":0}},{"duration":4,"tweenEasing":0,"value":{"aM":70}},{"duration":21}]},{"name":"blue","displayFrame":[{"duration":18,"value":-1},{"duration":22}],"colorFrame":[{"duration":27},{"duration":7,"tweenEasing":0},{"duration":6,"value":{"aM":0}}]},{"name":"logo","displayFrame":[{"duration":31,"value":-1},{"duration":9}],"colorFrame":[{"duration":31},{"duration":9,"tweenEasing":0,"value":{"aM":0,"rM":0,"gM":0,"bM":0}},{"duration":0}]},{"name":"blood","displayFrame":[{"duration":40}],"colorFrame":[{"duration":3,"tweenEasing":0,"value":{"aM":0}},{"duration":3,"tweenEasing":0},{"duration":23,"tweenEasing":0},{"duration":9,"tweenEasing":0,"value":{"aM":70}},{"duration":2,"value":{"aM":0}}]},{"name":"world","displayFrame":[{"duration":40}],"colorFrame":[{"duration":3,"tweenEasing":0,"value":{"aM":0}},{"duration":3,"tweenEasing":0},{"duration":23,"tweenEasing":0},{"duration":9,"tweenEasing":0,"value":{"aM":70}},{"duration":2,"value":{"aM":0}}]}]}],"defaultActions":[{"gotoAndPlay":"newAnimation"}]}]}